setup.py
login_szu/__init__.py
login_szu/decorator.py
login_szu/test.py
login_szu.egg-info/PKG-INFO
login_szu.egg-info/SOURCES.txt
login_szu.egg-info/dependency_links.txt
login_szu.egg-info/requires.txt
login_szu.egg-info/top_level.txt