Metadata-Version: 1.0
Name: login-szu
Version: 1.0.2
Summary: A package for login szu
Home-page: UNKNOWN
Author: jimczj
Author-email: jimczj@gmail.com
License: MIT License
Keywords: login_szu,szu
Platform: any
